[
  { "name": "藍白", "ruby": "あいじろ", "code": "#ebf6f7" },
  { "name": "白藍", "ruby": "しらあい", "code": "#c1e4e9" },
  { "name": "水色", "ruby": "みずいろ", "code": "#bce2e8" },
  { "name": "瓶覗", "ruby": "かめのぞき", "code": "#a2d7dd" },
  { "name": "秘色色", "ruby": "ひそくいろ", "code": "#abced8" },
  { "name": "空色", "ruby": "そらいろ", "code": "#a0d8ef" },
  { "name": "勿忘草色", "ruby": "わすれなぐさいろ", "code": "#89c3eb" },
  { "name": "白群", "ruby": "びゃくぐん", "code": "#83ccd2" },
  { "name": "浅縹", "ruby": "あさはなだ", "code": "#84b9cb" },
  { "name": "薄花色", "ruby": "うすはないろ", "code": "#698aab" },
  { "name": "納戸色", "ruby": "なんどいろ", "code": "#008899" },
  { "name": "浅葱色", "ruby": "あさぎいろ", "code": "#00a3af" },
  { "name": "花浅葱", "ruby": "はなあさぎ", "code": "#2a83a2" },
  { "name": "新橋色", "ruby": "しんばしいろ", "code": "#59b9c6" },
  { "name": "天色", "ruby": "あまいろ", "code": "#2ca9e1" },
  { "name": "露草色", "ruby": "つゆくさいろ", "code": "#38a1db" },
  { "name": "青", "ruby": "あお", "code": "#0095d9" },
  { "name": "薄藍", "ruby": "うすあい", "code": "#0094c8" },
  { "name": "縹色", "ruby": "はなだいろ", "code": "#2792c3" },
  { "name": "紺碧", "ruby": "こんぺき", "code": "#007bbb" },
  { "name": "薄群青", "ruby": "うすぐんじょう", "code": "#5383c3" },
  { "name": "薄花桜", "ruby": "うすはなざくら", "code": "#5a79ba" },
  { "name": "群青色", "ruby": "ぐんじょういろ", "code": "#4c6cb3" },
  { "name": "杜若色", "ruby": "かきつばたいろ", "code": "#3e62ad" },
  { "name": "瑠璃色", "ruby": "るりいろ", "code": "#1e50a2" },
  { "name": "薄縹", "ruby": "うすはなだ", "code": "#507ea4" },
  { "name": "瑠璃紺", "ruby": "るりこん", "code": "#19448e" },
  { "name": "紺瑠璃", "ruby": "こんるり", "code": "#164a84" },
  { "name": "藍色", "ruby": "あいいろ", "code": "#165e83" },
  { "name": "深縹", "ruby": "こきはなだ", "code": "#2a4073" },
  { "name": "紺色", "ruby": "こんいろ", "code": "#223a70" },
  { "name": "紺青", "ruby": "こんじょう", "code": "#192f60" },
  { "name": "留紺", "ruby": "とめこん", "code": "#1c305c" },
  { "name": "濃藍", "ruby": "こいあい", "code": "#0f2350" },
  { "name": "鉄紺", "ruby": "てつこん", "code": "#17184b" }
]